LICENSE
MANIFEST.in
README.md
requirements.txt
setup.py
tests/__init__.py
tests/compute_test.py
tests/process_test.py
tests/transform_log_test.py
timeseriesfeatures/__init__.py
timeseriesfeatures/cache.py
timeseriesfeatures/columns.py
timeseriesfeatures/compute.py
timeseriesfeatures/compute_acf.py
timeseriesfeatures/compute_arima.py
timeseriesfeatures/compute_nbeats.py
timeseriesfeatures/compute_pacf.py
timeseriesfeatures/feature.py
timeseriesfeatures/lag_process.py
timeseriesfeatures/non_categorical_numeric_columns.py
timeseriesfeatures/process.py
timeseriesfeatures/process_arima.py
timeseriesfeatures/process_nbeats.py
timeseriesfeatures/rolling_process.py
timeseriesfeatures/sanitise.py
timeseriesfeatures/shift_process.py
timeseriesfeatures/transform.py
timeseriesfeatures/transform_derivative.py
timeseriesfeatures/transform_log.py
timeseriesfeatures/transform_sma.py
timeseriesfeatures/transforms.py
timeseriesfeatures.egg-info/PKG-INFO
timeseriesfeatures.egg-info/SOURCES.txt
timeseriesfeatures.egg-info/dependency_links.txt
timeseriesfeatures.egg-info/not-zip-safe
timeseriesfeatures.egg-info/requires.txt
timeseriesfeatures.egg-info/top_level.txt