Metadata-Version: 2.1
Name: timeseriesfeatures
Version: 0.1.2
Summary: A library for processing timeseries features over a dataframe.
Home-page: https://github.com/8W9aG/timeseries-features
Author: Will Sackfield
Author-email: will.sackfield@gmail.com
License: MIT
Keywords: features,timeseries
Classifier: License :: OSI Approved :: MIT License
Classifier: Programming Language :: Python :: 3
License-File: LICENSE
Requires-Dist: pandas>=2.2.3
Requires-Dist: pyarrow>=19.0.1
Requires-Dist: statsmodels>=0.14.4
Requires-Dist: numpy<2,>=1.26.4
Requires-Dist: sktime>=0.37.0
Requires-Dist: pytorch-forecasting>=1.3.0
Requires-Dist: mlflow>=2.22.0
Requires-Dist: litmodels>=0.1.8
Requires-Dist: dill>=0.4.0
Requires-Dist: cloudpickle>=3.1.1
Requires-Dist: torch>=2.7.0
Requires-Dist: pmdarima>=2.0.4
